calchesoft/Calculator.py
calchesoft/__init__.py
calchesoft-0.0.1.dist-info/METADATA
calchesoft-0.0.1.dist-info/WHEEL
calchesoft-0.0.1.dist-info/license.txt
calchesoft-0.0.1.dist-info/top_level.txt
calchesoft-0.0.1.dist-info/RECORD
