Metadata-Version: 2.1
Name: calchesoft
Version: 0.0.1
Summary: Python Distribution Utilities
Home-page: https://github.com/hamzashoukat94/pythonAPP
Author: Hamza shoukat
Author-email: hamza_shoukat@diyatech.com
License: UNKNOWN
Platform: UNKNOWN
Requires-Python: >=3.6
